hytraj/__init__.py
hytraj/hyagg.py
hytraj/hycluster.py
hytraj/hygen.py
hytraj/hymodel.py
hytraj/hyplot.py
hytraj/hyread.py
hytraj-0.1.3.dist-info/LICENSE
hytraj-0.1.3.dist-info/METADATA
hytraj-0.1.3.dist-info/WHEEL
hytraj-0.1.3.dist-info/top_level.txt
hytraj-0.1.3.dist-info/RECORD
