Metadata-Version: 2.1
Name: hytraj
Version: 0.1.3
Summary: Implementation of HySPLIT based trajectory modeling and analysis in python
Home-page: https://github.com/pankajkarman/HyTraj
Author: Pankaj Kumar
Author-email: pankaj.kmr1990@gmail.com
License: MIT
Platform: UNKNOWN
Requires-Python: ==3.6
Requires-Dist: matplotlib (==3.2.1)
Requires-Dist: sklearn
Requires-Dist: PyWavelets
Requires-Dist: pyclustering
Requires-Dist: fastcluster
Requires-Dist: traj-dist
Requires-Dist: numpy
Requires-Dist: scipy
Requires-Dist: pandas
Requires-Dist: xarray
Requires-Dist: tqdm
